dask_regionprops/__init__.py
dask_regionprops/_version.py
dask_regionprops/regionprops.py
dask_regionprops/utils.py
dask_regionprops-0.3.1.dist-info/LICENSE
dask_regionprops-0.3.1.dist-info/METADATA
dask_regionprops-0.3.1.dist-info/WHEEL
dask_regionprops-0.3.1.dist-info/top_level.txt
dask_regionprops-0.3.1.dist-info/RECORD
