Metadata-Version: 2.1
Name: dask-regionprops
Version: 0.3.1
Summary: Compute region properties using dask delayed and dataframe
Home-page: https://github.com/jrussell25/dask-regionprops
Author: John Russell
Author-email: johncrussell25@gmail.com
License: BSD-3-Clause
Project-URL: Source Code, https://github.com/jrussell25/dask-regionprops
Classifier: Development Status :: 2 - Pre-Alpha
Classifier: License :: OSI Approved :: BSD License
Classifier: Natural Language :: English
Classifier: Programming Language :: Python :: 3
Classifier: Programming Language :: Python :: 3 :: Only
Classifier: Programming Language :: Python :: 3.7
Classifier: Programming Language :: Python :: 3.8
Classifier: Programming Language :: Python :: 3.9
Classifier: Programming Language :: Python :: Implementation :: CPython
Requires-Python: >=3.7
License-File: LICENSE
Requires-Dist: dask
Requires-Dist: numpy
Requires-Dist: pandas
Requires-Dist: scikit-image
Requires-Dist: xarray
Provides-Extra: dev
Requires-Dist: black ; extra == 'dev'
Requires-Dist: flake8 ; extra == 'dev'
Requires-Dist: flake8-docstrings ; extra == 'dev'
Requires-Dist: ipython ; extra == 'dev'
Requires-Dist: isort ; extra == 'dev'
Requires-Dist: jedi (<0.18.0) ; extra == 'dev'
Requires-Dist: mypy ; extra == 'dev'
Requires-Dist: pre-commit ; extra == 'dev'
Requires-Dist: pydocstyle ; extra == 'dev'
Requires-Dist: pytest ; extra == 'dev'
Provides-Extra: doc
Requires-Dist: Sphinx (>=1.5) ; extra == 'doc'
Requires-Dist: jupyter-sphinx ; extra == 'doc'
Requires-Dist: myst-nb ; extra == 'doc'
Requires-Dist: numpydoc ; extra == 'doc'
Requires-Dist: sphinx-book-theme ; extra == 'doc'
Requires-Dist: sphinx-copybutton ; extra == 'doc'
Requires-Dist: sphinx-panels ; extra == 'doc'
Requires-Dist: sphinx-thebe ; extra == 'doc'
Requires-Dist: sphinx-togglebutton ; extra == 'doc'
Provides-Extra: testing
Requires-Dist: nbval ; extra == 'testing'
Requires-Dist: pytest ; extra == 'testing'
Requires-Dist: pytest-cov ; extra == 'testing'
Requires-Dist: tox ; extra == 'testing'
Requires-Dist: tox-conda ; extra == 'testing'
